rin_zerochan/__init__.py
rin_zerochan/scrap.py
rin_zerochan/zerochan.py
src/__init__.py
src/scrap.py
src/zerochan.py
rin_zerochan-0.1.0.dist-info/LICENSE.txt
rin_zerochan-0.1.0.dist-info/METADATA
rin_zerochan-0.1.0.dist-info/WHEEL
rin_zerochan-0.1.0.dist-info/top_level.txt
rin_zerochan-0.1.0.dist-info/RECORD
