Metadata-Version: 2.1
Name: rin-zerochan
Version: 0.1.0
Summary: A simple and unofficial Python ZeroChan library.
Home-page: https://github.com/ArK7652/rin-zerochan
Author: ArK
Author-email: UNKNOWN
License: UNKNOWN
Platform: UNKNOWN
